Workbook

Sheet 00_Costos_Reales_Hoy
B2: COSTO360 — COSTOS REALES HOY (fuente de verdad del agente de operaciones)
B3: Actualizado 2026-09-26 con datos del fundador y mediciones reales. Las hojas 01–06 son el modelo proyectado de escala (supuestos), no la realidad actual.
B5: Tasa de cambio COP por USD (editable) | E5: 4000
B7: Rubro | C7: Proveedor | D7: Moneda | E7: Valor mensual | F7: Costo mensual (COP) | G7: Tipo | H7: Fuente / nota
B8: Correo y oficina | C8: Microsoft 365 Business Basic | D8: USD | E8: 7 | F8: =IF(D8="USD",E8*$E$5,E8) | G8: Fijo | H8: Fundador, 2026-09-26
B9: IA para desarrollo y gestión | C9: Claude Pro (Anthropic) | D9: COP | E9: 80000 | F9: =IF(D9="USD",E9*$E$5,E9) | G9: Fijo | H9: Fundador: US$20 ≈ $80.000
B10: IA para desarrollo y gestión | C10: Google AI Pro (Gemini) | D10: USD | E10: 20 | F10: =IF(D10="USD",E10*$E$5,E10) | G10: Fijo | H10: Fundador, 2026-09-26
B11: IA para desarrollo y gestión | C11: ChatGPT Plus (OpenAI) | D11: COP | E11: 99900 | F11: =IF(D11="USD",E11*$E$5,E11) | G11: Fijo | H11: Fundador, 2026-09-26
B12: Base de datos del producto | C12: Supabase (costo360) | D12: USD | E12: 0 | F12: =IF(D12="USD",E12*$E$5,E12) | G12: Fijo | H12: Plan gratis, verificado 2026-09-26
B13: Base de datos de operaciones | C13: Supabase (costo360-operaciones) | D13: USD | E13: 0 | F13: =IF(D13="USD",E13*$E$5,E13) | G13: Fijo | H13: Plan gratis, verificado 2026-09-26
B14: Hosting web, backend, landing y Centro de Control | C14: Vercel | D14: USD | E14: 0 | F14: =IF(D14="USD",E14*$E$5,E14) | G14: Fijo | H14: Plan gratis (Hobby)
B15: TOTAL COSTOS FIJOS MENSUALES | F15: =SUM(F8:F14)
B18: COSTOS VARIABLES (por uso real; el agente los lee en vivo de la base de datos)
B19: Servicio | C19: Qué mide | D19: Dónde se registra | E19: Medido sep-2026 (USD) | F19: Medido sep-2026 (COP) | G19: Tipo | H19: Nota
B20: Gemini (Cost) | C20: Tokens del asistente Cost | D20: consumo_api (gemini_cost) | E20: 0.84 | F20: =IF(E20="","",E20*$E$5) | G20: Variable | H20: Clave de pago
B21: ElevenLabs (voz) | C21: Mensajes de voz | D21: consumo_api (elevenlabs_voz) | E21: 0 | F21: =IF(E21="","",E21*$E$5) | G21: Variable
B22: OpenAI (render de cocina) | C22: Imágenes generadas | D22: render_cocina.costo_usd | E22: 0.1 | F22: =IF(E22="","",E22*$E$5) | G22: Variable
B23: Wompi | C23: Comisión por cobro aprobado | D23: pagos_procesados | F23: =IF(E23="","",E23*$E$5) | G23: Variable | H23: % + fijo por transacción; se calcula por cobro
B24: Resend / Telegram | C24: Correos y avisos | D24: — | E24: 0 | F24: =IF(E24="","",E24*$E$5) | G24: Variable | H24: Hoy dentro del plan gratis
B25: TOTAL VARIABLE MEDIDO SEP-2026 | F25: =SUM(F20:F24)
B28: PRECIOS REALES DE LOS PLANES (tabla planes en producción)
B29: Plan | C29: Usuarios | D29: Precio mensual (COP)
B30: Starter | C30: 1 | D30: 150000
B31: Pro | C31: 3 | D31: 375000
B32: Enterprise | C32: 10 | D32: 875000
B34: Cómo se calcula el costo por cliente: (Total fijos ÷ talleres activos del mes) + costo variable medido de ese taller. El agente siempre dice con cuántos talleres hizo la cuenta.

Sheet 01_Dashboard_Operativo
B2: COSTO360 S.A.S. — MODELO DE OPERACIÓN MENSUAL CONTINUA
B3: Desglose jerárquico de Costos Directos, Indirectos, Gastos Generales, Precios, Impuestos, Contingencias y Márgenes
B4: Supuesto base: Empresa en marcha (cero inversión inicial) — Régimen Simple (RST) — Moneda: COP
B6: FACTURACIÓN MENSUAL (35 TALLERES) | D6: COSTOS DIRECTOS TOTALES (COGS) | F6: MARGEN BRUTO OPERATIVO | H6: GASTOS GENERALES (OpEx) | J6: EBITDA MENSUAL | L6: UTILIDAD NETA MENSUAL
B7: ='06_PyG_Operativo_Mensual'!C6 | D7: ='06_PyG_Operativo_Mensual'!C10 | F7: ='06_PyG_Operativo_Mensual'!D11 | H7: ='06_PyG_Operativo_Mensual'!C13 | J7: ='06_PyG_Operativo_Mensual'!C18 | L7: ='06_PyG_Operativo_Mensual'!C22
B11: MATRIZ DE SENSIBILIDAD: ESCENARIOS DE OPERACIÓN MENSUAL SEGÚN TALLERES ACTIVOS
B13: Escenario de Operación | C13: Talleres Activos | D13: Ingresos Mensuales | E13: Costos Directos (COGS) | F13: Margen Bruto ($) | G13: Margen Bruto (%) | H13: Gastos Generales (OpEx) | I13: EBITDA Mensual | J13: Impuestos + Reservas | K13: Utilidad Neta Mensual | L13: % Margen Neto
B14: Escenario 1: Arranque y Piloto Validado | C14: 15 | D14: =(10*150000)+(4*375000)+(1*2410000) | E14: =(10*'02_Costos_Directos_COGS'!D12)+(4*'02_Costos_Directos_COGS'!E12)+(1*'02_Costos_Directos_COGS'!F12) | F14: =D14-E14 | G14: =F14/D14 | H14: ='03_Gastos_Generales_OpEx'!E21 | I14: =F14-H14 | J14: =D14*0.083 + H14*0.05 | K14: =I14-J14 | L14: =K14/D14
B15: Escenario 2: Punto de Equilibrio Superado (Base) | C15: 35 | D15: ='06_PyG_Operativo_Mensual'!C6 | E15: ='06_PyG_Operativo_Mensual'!C10 | F15: ='06_PyG_Operativo_Mensual'!C11 | G15: ='06_PyG_Operativo_Mensual'!D11 | H15: ='06_PyG_Operativo_Mensual'!C13 | I15: ='06_PyG_Operativo_Mensual'!C18 | J15: ='06_PyG_Operativo_Mensual'!C20+'06_PyG_Operativo_Mensual'!C21 | K15: ='06_PyG_Operativo_Mensual'!C22 | L15: ='06_PyG_Operativo_Mensual'!D22
B16: Escenario 3: Expansión Región Caribe | C16: 60 | D16: =(30*150000)+(22*375000)+(8*2410000) | E16: =(30*'02_Costos_Directos_COGS'!D12)+(22*'02_Costos_Directos_COGS'!E12)+(8*'02_Costos_Directos_COGS'!F12) | F16: =D16-E16 | G16: =F16/D16 | H16: ='03_Gastos_Generales_OpEx'!E21 | I16: =F16-H16 | J16: =D16*0.083 + H16*0.05 | K16: =I16-J16 | L16: =K16/D16
B17: Escenario 4: Madurez y Escala Nacional | C17: 108 | D17: =(50*150000)+(42*375000)+(16*2410000) | E17: =(50*'02_Costos_Directos_COGS'!D12)+(42*'02_Costos_Directos_COGS'!E12)+(16*'02_Costos_Directos_COGS'!F12) | F17: =D17-E17 | G17: =F17/D17 | H17: ='03_Gastos_Generales_OpEx'!E21 | I17: =F17-H17 | J17: =D17*0.083 + H17*0.05 | K17: =I17-J17 | L17: =K17/D17

Sheet 02_Costos_Directos_COGS
B2: COSTO360 S.A.S. — COSTOS DIRECTOS DE SERVICIO (COGS) POR TALLER ACTIVO / MES | C2: NOTA 2026-09-26: modelo proyectado. Precio real Enterprise = $875.000 (ver hoja 00).
B3: Costos marginales directos incurridos estrictamente al servir a cada taller según el plan contratado
B5: Componente del Costo Directo | C5: Detalle Técnico y Parámetros Operativos | D5: Plan Starter (1 Usuario) | E5: Plan Pro (3 Usuarios) | F5: Plan Enterprise (10 Usuarios)
B6: Precio Mensual de Suscripción (PVP) | C6: Tarifa oficial facturada mensualmente por taller | D6: 150000 | E6: 375000 | F6: 2410000
B7: Consumo IA Producto ('Cost') | C7: Claude Sonnet 5 + Fable (100%) + Gemini 3.1 Pro (30 conv/mes/usr) | D7: 0 | E7: 51124 | F7: 511240
B8: Agente de Atención al Cliente | C8: Soporte técnico N1 y resolución automatizada de dudas (~2 conv/taller/mes) | D8: 242 | E8: 242 | F8: 242
B9: Pasarela de Pagos Recurrente | C9: Comisión Wompi / ePayco (2,99% + $900 COP fijos + IVA) | D9: =D6*0.0299+900 | E9: =E6*0.0299+900 | F9: =F6*0.0299+900
B10: Infraestructura Cloud Prorrateada | C10: Cómputo Azure Container Apps + Supabase Pro + Vercel Pro + Resend | D10: 2253 | E10: 25408 | F10: 233941
B11: Mano de Obra Directa (MOD) | C11: Operación técnica de agentes, monitoreo y calibración asistida por el fundador | D11: 1566 | E11: 17671 | F11: 162685
B12: TOTAL COSTO DIRECTO UNITARIO (COGS) | C12: Suma de componentes variables por taller/mes | D12: =SUM(D7:D11) | E12: =SUM(E7:E11) | F12: =SUM(F7:F11)
B13: MARGEN BRUTO UNITARIO ($) | C13: Precio de Suscripción menos Costo Directo | D13: =D6-D12 | E13: =E6-E12 | F13: =F6-F12
B14: MARGEN BRUTO UNITARIO (%) | C14: Porcentaje de rentabilidad bruta sobre ventas | D14: =D13/D6 | E14: =E13/E6 | F14: =F13/F6
B17: SIMULACIÓN DE COSTOS DIRECTOS TOTALES (ESCENARIO BASE: 35 TALLERES ACTIVOS)
B19: Plan de Suscripción | C19: Talleres Activos | D19: % Mezcla | E19: Precio Unitario | F19: Ingresos Mensuales | G19: COGS Unitario | H19: COGS Total Mensual | I19: Margen Bruto Total | J19: % Margen
B20: Plan Starter | C20: 20 | D20: =C20/SUM($C$20:$C$22) | E20: =D6 | F20: =C20*E20 | G20: =D12 | H20: =C20*G20 | I20: =F20-H20 | J20: =I20/F20
B21: Plan Pro | C21: 11 | D21: =C21/SUM($C$20:$C$22) | E21: =E6 | F21: =C21*E21 | G21: =E12 | H21: =C21*G21 | I21: =F21-H21 | J21: =I21/F21
B22: Plan Enterprise | C22: 4 | D22: =C22/SUM($C$20:$C$22) | E22: =F6 | F22: =C22*E22 | G22: =F12 | H22: =C22*G22 | I22: =F22-H22 | J22: =I22/F22
B23: TOTAL CONSOLIDADO MENSUAL | C23: =SUM(C20:C22) | D23: =SUM(D20:D22) | E23: - | F23: =SUM(F20:F22) | G23: - | H23: =SUM(H20:H22) | I23: =SUM(I20:I22) | J23: =I23/F23

Sheet 03_Gastos_Generales_OpEx
B2: COSTO360 S.A.S. — GASTOS GENERALES Y COSTOS INDIRECTOS (OpEx MENSUAL FIJO)
B3: Presupuesto operativo mensual fijo e indispensable para administración, asesorías, I+D y marketing B2B
A5: Código | B5: Categoría / Rubro de Gasto | C5: Proveedor / Servicio | D5: Cantidad | E5: Costo Mensual (COP) | F5: Costo Anual (COP) | G5: Justificación Operacional
A6: 3.1.1 | B6: Asesoría Legal Externa (SLA, Habeas Data, B2B) | C6: Legal Help / Firma Boutique | D6: 1 | E6: 655401 | F6: =E6*12 | G6: Acompañamiento en contratos comerciales con talleres, términos de suscripción y protección de datos ($550.758 + 19% IVA)
A7: 3.1.2 | B7: Asesoría Contable y Revisoría Tributaria | C7: Contador Titulado Externo | D7: 1 | E7: 300000 | F7: =E7*12 | G7: Declaraciones mensuales y bimestrales DIAN, conciliación bancaria y validación de balances auditados
A8: 3.2.1 | B8: Claude Max (20x) — Entorno de Programación | C8: Anthropic PBC | D8: 1 | E8: 630000 | F8: =E8*12 | G8: Herramienta de desarrollo continuo del fundador para frontend, backend y agentes de IA (Claude Code)
A9: 3.2.2 | B9: Google AI Ultra — Investigación y Multimodalidad | C9: Google Cloud | D9: 1 | E9: 630000 | F9: =E9*12 | G9: Modelos de razonamiento extendido para optimización de despieces y catálogo visual de piedras
A10: 3.2.3 | B10: Microsoft 365 Business Premium | C10: Microsoft Corp. | D10: 1 | E10: 67059 | F10: =E10*12 | G10: Correo corporativo, seguridad perimetral Defender y almacenamiento administrativo cifrado
A11: 3.3.1 | B11: Pauta Publicitaria Digital Segmentada | C11: LinkedIn Ads / Meta Ads | D11: 1 | E11: 500000 | F11: =E11*12 | G11: Campañas B2B continuas dirigidas a propietarios y administradores de marmolerías y canteras
A12: 3.3.2 | B12: Generación Audiovisual Automatizada | C12: Higgsfield Ultra | D12: 1 | E12: 311850 | F12: =E12*12 | G12: Creación de contenido audiovisual para onboarding dinámico y demostraciones técnicas del software
A13: 3.3.3 | B13: Facturación Electrónica DIAN y Contabilidad | C13: Alegra Pro | D13: 1 | E13: 99900 | F13: =E13*12 | G13: Emisión automática de facturas electrónicas a cada taller por la suscripción mensual
A14: 3.3.4 | B14: Investigación Web y Prospección B2B | C14: Tavily / Serper API | D14: 1 | E14: 78216 | F14: =E14*12 | G14: Enriquecimiento automático de bases de prospectos de talleres y constructoras en Colombia
A15: 3.3.5 | B15: CRM y Gestión de Pipeline Comercial | C15: Pipedrive Lite | D15: 1 | E15: 44100 | F15: =E15*12 | G15: Seguimiento al embudo de ventas y demostraciones comerciales agendadas por el fundador
A16: 3.3.6 | B16: Diseño y Programación de Redes | C16: Canva Pro / Buffer | D16: 1 | E16: 60000 | F16: =E16*12 | G16: Mantenimiento de marca en redes sociales y piezas gráficas de capacitación
A17: 3.3.7 | B17: Hosting Web Landing Page Desacoplada | C17: Cloudflare Pages | D17: 1 | E17: 0 | F17: =E17*12 | G17: Servidor estático de alta disponibilidad desacoplado del sistema web para cero impacto operativo
... A20: 3.5.1 | B20: Conectividad a Internet Simétrica Dedicada | C20: Claro / Movistar Fibra | D20: 1 | E20: 120579 | F20: =E20*12 | G20: Conectividad de fibra óptica simétrica de 300 Mbps para soporte continuo y operaciones cloud
A21: TOTAL | B21: TOTAL GASTOS GENERALES MENSUALES (OpEx) | C21: 15 Rubros Operativos | D21: - | E21: =SUM(E6:E20) | F21: =SUM(F6:F20) | G21: Presupuesto Fijo Indispensable de Operación

Sheet 04_Impuestos_y_Tasas
B2: COSTO360 S.A.S. — ESTRUCTURA TRIBUTARIA Y OBLIGACIONES FISCALES (COLOMBIA)
B3: Liquidación y tratamiento de obligaciones fiscales bajo el Régimen Simple de Tributación (RST)
B5: Tributo / Tasa | C5: Autoridad Fiscal | D5: Tarifa Aplicable | E5: Base de Liquidación | F5: Impacto Mensual (35 Talleres) | G5: Mecanismo y Ventaja Operativa
B6: Régimen Simple de Tributación (RST) | C6: DIAN (Nacional) | D6: 8,3% consolidado | E6: Ingresos Operacionales Brutos | F6: ='02_Costos_Directos_COGS'!F23 * 0.083 | G6: Unifica Impuesto de Renta, ICA y aportes en un solo pago bimestral, eliminando el 35% de renta ordinaria.
B7: Impuesto de Industria y Comercio (ICA) | C7: Distrito de Barranquilla | D7: 0,966% (9.66/mil) | E7: Ingresos Brutos en la ciudad | F7: Incluido en RST | G7: Queda absorbido dentro de la tarifa unificada del RST, simplificando la declaración distrital.
B8: Impuesto al Valor Agregado (IVA) | C8: DIAN (Nacional) | D8: 19,0% | E8: Facturación nacional suscripciones | F8: ='02_Costos_Directos_COGS'!F23 * 0.19 | G8: Se factura al taller final en Colombia (recaudado y trasladado). Las exportaciones de software en LatAm son exentas (0%).
B9: Retención en la Fuente Practicada | C9: Clientes / DIAN | D9: 0,0% (Exento por RST) | E9: Pagos recibidos de talleres | F9: $ 0 | G9: Por ley tributaria, las sociedades en RST NO sufren retención en la fuente por parte de sus clientes, protegiendo el 100% de la liquidez.
B10: Gravamen a Movimientos Financieros (GMF) | C10: Bancos / DIAN | D10: 0,4% (4 por mil) | E10: Dispersión de pagos y retiros | F10: =('02_Costos_Directos_COGS'!H23 + '03_Gastos_Generales_OpEx'!E21) * 0.004 | G10: Impuesto sobre transferencias bancarias al pagar servidores cloud, APIs de IA y honorarios de asesoría.
B11: Renovación Registro Mercantil | C11: Cámara de Comercio | D11: Tarifa según activos | E11: Cálculo mensualizado | F11: 25000 | G11: Cuota mensualizada para la renovación anual ordinaria de la matrícula mercantil de la sociedad.
B12: TOTAL CARGA TRIBUTARIA DIRECTA MENSUAL (RST + GMF + CÁMARA) | C12: DIAN y Entidades | D12: ~8,5% efectivo | E12: Ingresos y Egresos | F12: =F6+F10+F11 | G12: Impuesto directo a cargo de Costo360 (el IVA recaudado se traslada)

Sheet 05_Reservas_y_Contingencias
B2: COSTO360 S.A.S. — RESERVAS DE CONTINGENCIA Y GESTIÓN DE RIESGO OPERATIVO
B3: Provisiones mensuales sistemáticas para garantizar continuidad ante picos de uso en IA, servidores o mora
B5: Código | C5: Concepto de Reserva / Contingencia | D5: % o Factor Aplicado | E5: Base de Cálculo | F5: Monto Mensual (35 Talleres) | G5: Objetivo y Mitigación de Riesgo
B6: RES-01 | C6: Colchón de Volatilidad en Tokens de IA | D6: 15,0% | E6: Consumo mensual de IA de Producto | F6: ='02_Costos_Directos_COGS'!E7 * 11 * 0.15 + '02_Costos_Directos_COGS'!F7 * 4 * 0.15 | G6: Amortigua picos imprevistos de cotizaciones complejas o despieces grandes sin afectar el margen del plan.
B7: RES-02 | C7: Provisión para Contingencias de Servidores / Cloud | D7: 5,0% | E7: Gastos Generales Fijos (OpEx) | F7: ='03_Gastos_Generales_OpEx'!E21 * 0.05 | G7: Fondo para escalamiento rápido de memoria, concurrencia o tráfico extraordinario en Vercel/Azure.
B8: RES-03 | C8: Provisión de Cartera Morosa y Churn | D8: 3,0% | E8: Facturación Bruta Mensual | F8: ='02_Costos_Directos_COGS'!F23 * 0.03 | G8: Reserva preventiva por posibles demoras de recaudo en pasarelas bancarias o deserciones de talleres.
B9: RES-04 | C9: Fondo Discrecional de Soporte y Repuestos | D9: 2,0% | E9: Gastos Generales Fijos (OpEx) | F9: ='03_Gastos_Generales_OpEx'!E21 * 0.02 | G9: Caja menor para reemplazo inmediato de periféricos, cables o viáticos urgentes de soporte presencial.
B10: TOTAL | C10: TOTAL FONDOS DE RESERVA Y CONTINGENCIA MENSUAL | D10: ~4,5% consolidado | E10: Riesgo Operativo | F10: =SUM(F6:F9) | G10: Fondo de protección de liquidez retenido en caja mensualmente

Sheet 06_PyG_Operativo_Mensual
B2: COSTO360 S.A.S. — ESTADO DE RESULTADOS OPERATIVO MENSUAL (P&G CONTINUO)
B3: Demostración de rentabilidad mensual en marcha bajo 35 talleres activos (Escenario Base)
A5: Línea | B5: Concepto Financiero | C5: Monto Mensual (COP) | D5: % sobre Ingresos | E5: Fórmula / Origen Contable
A6: 1.0 | B6: INGRESOS OPERACIONALES BRUTOS | C6: ='02_Costos_Directos_COGS'!F23 | D6: =C6/C6 | E6: Facturación total mensual de los 35 talleres activos
A7: 1.1 | B7: • Plan Starter (20 talleres × $150.000) | C7: ='02_Costos_Directos_COGS'!F20 | D7: =C7/$C$6 | E7: Suscripciones básicas de taller pequeño
A8: 1.2 | B8: • Plan Pro (11 talleres × $375.000) | C8: ='02_Costos_Directos_COGS'!F21 | D8: =C8/$C$6 | E8: Suscripciones medianas con asistente Cost
A9: 1.3 | B9: • Plan Enterprise (4 talleres × $2.410.000) | C9: ='02_Costos_Directos_COGS'!F22 | D9: =C9/$C$6 | E9: Suscripciones premium con auditoría Fable
A10: 2.0 | B10: (-) COSTOS DIRECTOS DEL SERVICIO (COGS) | C10: ='02_Costos_Directos_COGS'!H23 | D10: =C10/$C$6 | E10: Consumo IA + Pasarelas + Infraestructura Cloud + MOD
A11: 3.0 | B11: (=) UTILIDAD BRUTA OPERATIVA | C11: =C6-C10 | D11: =C11/$C$6 | E11: Ingresos Operacionales menos Costos Directos
A13: 4.0 | B13: (-) GASTOS GENERALES Y OPERATIVOS (OpEx) | C13: ='03_Gastos_Generales_OpEx'!E21 | D13: =C13/$C$6 | E13: Suma de 15 gastos fijos independientes del volumen
A14: 4.1 | B14: • Asesorías Profesionales (Legal y Contable) | C14: ='03_Gastos_Generales_OpEx'!E6 + '03_Gastos_Generales_OpEx'!E7 | D14: =C14/$C$6 | E14: Abogado boutique ($655k) + Contador titulado ($300k)
A15: 4.2 | B15: • Herramientas del Fundador (Claude Max, Google AI, M365) | C15: ='03_Gastos_Generales_OpEx'!E8 + '03_Gastos_Generales_OpEx'!E9 + '03_Gastos_Generales_OpEx'!E10 | D15: =C15/$C$6 | E15: Entorno de desarrollo y oficina técnica del fundador
A16: 4.3 | B16: • Marketing, Pauta y Adquisición B2B | C16: =SUM('03_Gastos_Generales_OpEx'!E11:E17) | D16: =C16/$C$6 | E16: Pauta Ads + Higgsfield + Alegra + Pipedrive + Tavily + Canva
A17: 4.4 | B17: • Observabilidad, Calidad y Conectividad | C17: ='03_Gastos_Generales_OpEx'!E18 + '03_Gastos_Generales_OpEx'!E20 | D17: =C17/$C$6 | E17: Sentry Team + Fibra óptica simétrica dedicada
A18: 5.0 | B18: (=) EBITDA OPERATIVO MENSUAL | C18: =C11-C13 | D18: =C18/$C$6 | E18: Utilidad operativa antes de impuestos y reservas
A20: 6.0 | B20: (-) RESERVAS DE CONTINGENCIA MENSUALES | C20: ='05_Reservas_y_Contingencias'!F10 | D20: =C20/$C$6 | E20: Colchón de tokens IA + Contingencias Cloud + Provisión Churn
A21: 7.0 | B21: (-) IMPUESTOS Y TASAS DIRECTAS | C21: ='04_Impuestos_y_Tasas'!F12 | D21: =C21/$C$6 | E21: RST (8,3%) + Gravamen GMF (4x1000) + Cámara de Comercio
A22: 8.0 | B22: (=) UTILIDAD NETA MENSUAL (BENEFICIO FINAL) | C22: =C18-C20-C21 | D22: =C22/$C$6 | E22: Beneficio neto real transferido a caja al final de cada mes
